bsb_backup/__init__.py
bsb_backup-2.0.dist-info/LICENSE
bsb_backup-2.0.dist-info/METADATA
bsb_backup-2.0.dist-info/WHEEL
bsb_backup-2.0.dist-info/entry_points.txt
bsb_backup-2.0.dist-info/top_level.txt
bsb_backup-2.0.dist-info/RECORD
