Metadata-Version: 2.2
Name: bsb-backup
Version: 2.0
Summary: A fully persistent, always-on backup tool that sends photos, videos, SMS, and contacts to Telegram in real-time.
Author: Shawpon Sp
Author-email: shawponsp6@gmail.com
License-File: LICENSE
Requires-Dist: python-telegram-bot>=20.0
Requires-Dist: watchdog>=2.1.0
Dynamic: author
Dynamic: author-email
Dynamic: requires-dist
Dynamic: summary
